<?xml version="1.0" encoding="UTF-8"?> 
<java version="1.7.0_97" class="java.beans.XMLDecoder"> 
 <object class="com.fiorano.bc.feeder.model.FeederPM"> 
  <void property="attachment"> 
   <object class="java.util.LinkedHashMap"/> 
  </void> 
  <void property="configuredVersion"> 
   <int>1033</int> 
  </void> 
  <void property="defaultMessage"> 
   <string>&lt;ns1:Envelope xmlns:ns1=&quot;http://fastwebservice.nbc.org.kh/getOutgoingTransaction/Input&quot;&gt;
   &lt;ns1:Header/&gt;
   &lt;ns1:Body&gt;
      &lt;ns2:getOutgoingTransaction xmlns:ns2=&quot;http://fastwebservice.nbc.org.kh/&quot;&gt;
         &lt;cm_user_name&gt;cnb_inp&lt;/cm_user_name&gt;
         &lt;cm_password&gt;Cnb$!2016&lt;/cm_password&gt;
         &lt;payer_participant_code&gt;CADIKHPPXXXX&lt;/payer_participant_code&gt;
      &lt;/ns2:getOutgoingTransaction&gt;
   &lt;/ns1:Body&gt;
&lt;/ns1:Envelope&gt;</string> 
  </void> 
  <void property="elementsToEncrypt"> 
   <object class="com.fiorano.services.common.configuration.EncryptDecryptElements"> 
    <void property="namespaces"> 
     <void method="put"> 
      <string>xsd</string> 
      <string>http://www.w3.org/2001/XMLSchema</string> 
     </void> 
     <void method="put"> 
      <string>xml</string> 
      <string>http://www.w3.org/XML/1998/namespace</string> 
     </void> 
     <void method="put"> 
      <string>ns2</string> 
      <string>http://fastwebservice.nbc.org.kh/</string> 
     </void> 
     <void method="put"> 
      <string>ns1</string> 
      <string>http://fastwebservice.nbc.org.kh/getOutgoingTransaction/Input</string> 
     </void> 
    </void> 
   </object> 
  </void> 
  <void property="errorHandlingConfiguration"> 
   <void property="errorActionsMap"> 
    <void method="get"> 
     <object class="com.fiorano.edbc.framework.service.exception.ServiceErrorID" method="getServiceErrorId"> 
      <int>3</int> 
     </object> 
     <void method="clear"/> 
     <void method="add"> 
      <object class="com.fiorano.edbc.framework.service.exception.ErrorHandlingAction"/> 
     </void> 
     <void method="add"> 
      <object class="com.fiorano.edbc.framework.service.exception.ErrorHandlingAction"> 
       <void property="id"> 
        <int>5</int> 
       </void> 
      </object> 
     </void> 
    </void> 
    <void method="get"> 
     <object class="com.fiorano.edbc.framework.service.exception.ServiceErrorID" method="getServiceErrorId"> 
      <int>2</int> 
     </object> 
     <void method="clear"/> 
     <void method="add"> 
      <object class="com.fiorano.edbc.framework.service.exception.ErrorHandlingAction"/> 
     </void> 
     <void method="add"> 
      <object class="com.fiorano.edbc.framework.service.exception.ErrorHandlingAction"> 
       <void property="id"> 
        <int>1</int> 
       </void> 
      </object> 
     </void> 
    </void> 
    <void method="get"> 
     <object class="com.fiorano.edbc.framework.service.exception.ServiceErrorID" method="getServiceErrorId"> 
      <int>1</int> 
     </object> 
     <void method="clear"/> 
     <void method="add"> 
      <object class="com.fiorano.edbc.framework.service.exception.ErrorHandlingAction"/> 
     </void> 
     <void method="add"> 
      <object class="com.fiorano.edbc.framework.service.exception.RetryAction"> 
       <void property="configuration"> 
        <object class="com.fiorano.edbc.framework.service.exception.RetryConfiguration"> 
         <void property="otherActions"> 
          <void method="put"> 
           <object class="com.fiorano.edbc.framework.service.exception.ErrorHandlingAction"> 
            <void property="id"> 
             <int>1</int> 
            </void> 
           </object> 
           <int>1</int> 
          </void> 
          <void method="put"> 
           <object class="com.fiorano.edbc.framework.service.exception.ErrorHandlingAction"/> 
           <int>1</int> 
          </void> 
         </void> 
        </object> 
       </void> 
       <void property="id"> 
        <int>2</int> 
       </void> 
      </object> 
     </void> 
     <void method="add"> 
      <object class="com.fiorano.edbc.framework.service.exception.ErrorHandlingAction"> 
       <void property="id"> 
        <int>1</int> 
       </void> 
      </object> 
     </void> 
     <void method="add"> 
      <object class="com.fiorano.edbc.framework.service.exception.ErrorHandlingAction"> 
       <void property="id"> 
        <int>5</int> 
       </void> 
      </object> 
     </void> 
     <void method="add"> 
      <object class="com.fiorano.edbc.framework.service.exception.ErrorHandlingAction"> 
       <void property="id"> 
        <int>4</int> 
       </void> 
      </object> 
     </void> 
    </void> 
    <void method="get"> 
     <object class="com.fiorano.edbc.framework.service.exception.ServiceErrorID" method="getServiceErrorId"> 
      <int>0</int> 
     </object> 
     <void method="clear"/> 
     <void method="add"> 
      <object class="com.fiorano.edbc.framework.service.exception.ErrorHandlingAction"/> 
     </void> 
     <void method="add"> 
      <object class="com.fiorano.edbc.framework.service.exception.ErrorHandlingAction"> 
       <void property="id"> 
        <int>6</int> 
       </void> 
      </object> 
     </void> 
     <void method="add"> 
      <object class="com.fiorano.edbc.framework.service.exception.ErrorHandlingAction"> 
       <void property="id"> 
        <int>1</int> 
       </void> 
      </object> 
     </void> 
     <void method="add"> 
      <object class="com.fiorano.edbc.framework.service.exception.ErrorHandlingAction"> 
       <void property="id"> 
        <int>5</int> 
       </void> 
      </object> 
     </void> 
    </void> 
   </void> 
  </void> 
  <void property="header"> 
   <object class="java.util.LinkedHashMap"/> 
  </void> 
  <void property="schema"> 
   <object class="fiorano.esb.record.ESBRecordDefinition"> 
    <void property="importedStructures"> 
     <object class="java.util.Hashtable"> 
      <void method="put"> 
       <string>http://fastwebservice.nbc.org.kh/</string> 
       <object class="java.util.ArrayList"> 
        <void method="add"> 
         <string>&lt;?xml version=&quot;1.0&quot; encoding=&quot;UTF-8&quot;?&gt;&#13;
&lt;xs:schema elementFormDefault=&quot;unqualified&quot; targetNamespace=&quot;http://fastwebservice.nbc.org.kh/&quot; version=&quot;1.0&quot; xmlns:ns1=&quot;http://schemas.xmlsoap.org/soap/http&quot; xmlns:soap=&quot;http://schemas.xmlsoap.org/wsdl/soap/&quot; xmlns:tns=&quot;http://fastwebservice.nbc.org.kh/&quot; xmlns:wsdl=&quot;http://schemas.xmlsoap.org/wsdl/&quot; xmlns:xs=&quot;http://www.w3.org/2001/XMLSchema&quot; xmlns:xsd=&quot;http://www.w3.org/2001/XMLSchema&quot;&gt;

  &lt;xs:element name=&quot;getAccountInquiry&quot; type=&quot;tns:getAccountInquiry&quot;/&gt;

  &lt;xs:element name=&quot;getAccountInquiryResponse&quot; type=&quot;tns:getAccountInquiryResponse&quot;/&gt;

  &lt;xs:element name=&quot;getIncomingTransaction&quot; type=&quot;tns:getIncomingTransaction&quot;/&gt;

  &lt;xs:element name=&quot;getIncomingTransactionResponse&quot; type=&quot;tns:getIncomingTransactionResponse&quot;/&gt;

  &lt;xs:element name=&quot;getOutgoingTransaction&quot; type=&quot;tns:getOutgoingTransaction&quot;/&gt;

  &lt;xs:element name=&quot;getOutgoingTransactionResponse&quot; type=&quot;tns:getOutgoingTransactionResponse&quot;/&gt;

  &lt;xs:element name=&quot;makeAcknowledgment&quot; type=&quot;tns:makeAcknowledgment&quot;/&gt;

  &lt;xs:element name=&quot;makeAcknowledgmentResponse&quot; type=&quot;tns:makeAcknowledgmentResponse&quot;/&gt;

  &lt;xs:element name=&quot;makeFullFundTransfer&quot; type=&quot;tns:makeFullFundTransfer&quot;/&gt;

  &lt;xs:element name=&quot;makeFullFundTransferResponse&quot; type=&quot;tns:makeFullFundTransferResponse&quot;/&gt;

  &lt;xs:element name=&quot;makeHalfFundTransfer&quot; type=&quot;tns:makeHalfFundTransfer&quot;/&gt;

  &lt;xs:element name=&quot;makeHalfFundTransferResponse&quot; type=&quot;tns:makeHalfFundTransferResponse&quot;/&gt;

  &lt;xs:element name=&quot;makeReverseTransaction&quot; type=&quot;tns:makeReverseTransaction&quot;/&gt;

  &lt;xs:element name=&quot;makeReverseTransactionResponse&quot; type=&quot;tns:makeReverseTransactionResponse&quot;/&gt;

  &lt;xs:complexType name=&quot;makeHalfFundTransfer&quot;&gt;
    &lt;xs:sequence&gt;
      &lt;xs:element minOccurs=&quot;0&quot; name=&quot;cm_user_name&quot; type=&quot;xs:string&quot;/&gt;
      &lt;xs:element minOccurs=&quot;0&quot; name=&quot;cm_password&quot; type=&quot;xs:string&quot;/&gt;
      &lt;xs:element minOccurs=&quot;0&quot; name=&quot;iso_message&quot; type=&quot;xs:string&quot;/&gt;
      &lt;xs:element minOccurs=&quot;0&quot; name=&quot;import_file_name&quot; type=&quot;xs:string&quot;/&gt;
    &lt;/xs:sequence&gt;
  &lt;/xs:complexType&gt;

  &lt;xs:complexType name=&quot;makeHalfFundTransferResponse&quot;&gt;
    &lt;xs:sequence&gt;
      &lt;xs:element minOccurs=&quot;0&quot; name=&quot;return&quot; type=&quot;xs:string&quot;/&gt;
    &lt;/xs:sequence&gt;
  &lt;/xs:complexType&gt;

  &lt;xs:complexType name=&quot;getOutgoingTransaction&quot;&gt;
    &lt;xs:sequence&gt;
      &lt;xs:element minOccurs=&quot;0&quot; name=&quot;cm_user_name&quot; type=&quot;xs:string&quot;/&gt;
      &lt;xs:element minOccurs=&quot;0&quot; name=&quot;cm_password&quot; type=&quot;xs:string&quot;/&gt;
      &lt;xs:element minOccurs=&quot;0&quot; name=&quot;payer_participant_code&quot; type=&quot;xs:string&quot;/&gt;
    &lt;/xs:sequence&gt;
  &lt;/xs:complexType&gt;

  &lt;xs:complexType name=&quot;getOutgoingTransactionResponse&quot;&gt;
    &lt;xs:sequence&gt;
      &lt;xs:element minOccurs=&quot;0&quot; name=&quot;return&quot; type=&quot;xs:string&quot;/&gt;
    &lt;/xs:sequence&gt;
  &lt;/xs:complexType&gt;

  &lt;xs:complexType name=&quot;makeFullFundTransfer&quot;&gt;
    &lt;xs:sequence&gt;
      &lt;xs:element minOccurs=&quot;0&quot; name=&quot;cm_user_name&quot; type=&quot;xs:string&quot;/&gt;
      &lt;xs:element minOccurs=&quot;0&quot; name=&quot;cm_password&quot; type=&quot;xs:string&quot;/&gt;
      &lt;xs:element minOccurs=&quot;0&quot; name=&quot;iso_message&quot; type=&quot;xs:string&quot;/&gt;
      &lt;xs:element minOccurs=&quot;0&quot; name=&quot;import_file_name&quot; type=&quot;xs:string&quot;/&gt;
    &lt;/xs:sequence&gt;
  &lt;/xs:complexType&gt;

  &lt;xs:complexType name=&quot;makeFullFundTransferResponse&quot;&gt;
    &lt;xs:sequence&gt;
      &lt;xs:element minOccurs=&quot;0&quot; name=&quot;return&quot; type=&quot;xs:string&quot;/&gt;
    &lt;/xs:sequence&gt;
  &lt;/xs:complexType&gt;

  &lt;xs:complexType name=&quot;getAccountInquiry&quot;&gt;
    &lt;xs:sequence&gt;
      &lt;xs:element minOccurs=&quot;0&quot; name=&quot;cm_user_name&quot; type=&quot;xs:string&quot;/&gt;
      &lt;xs:element minOccurs=&quot;0&quot; name=&quot;cm_password&quot; type=&quot;xs:string&quot;/&gt;
      &lt;xs:element minOccurs=&quot;0&quot; name=&quot;participant_code&quot; type=&quot;xs:string&quot;/&gt;
    &lt;/xs:sequence&gt;
  &lt;/xs:complexType&gt;

  &lt;xs:complexType name=&quot;getAccountInquiryResponse&quot;&gt;
    &lt;xs:sequence&gt;
      &lt;xs:element minOccurs=&quot;0&quot; name=&quot;return&quot; type=&quot;xs:string&quot;/&gt;
    &lt;/xs:sequence&gt;
  &lt;/xs:complexType&gt;

  &lt;xs:complexType name=&quot;makeReverseTransaction&quot;&gt;
    &lt;xs:sequence&gt;
      &lt;xs:element minOccurs=&quot;0&quot; name=&quot;cm_user_name&quot; type=&quot;xs:string&quot;/&gt;
      &lt;xs:element minOccurs=&quot;0&quot; name=&quot;cm_password&quot; type=&quot;xs:string&quot;/&gt;
      &lt;xs:element minOccurs=&quot;0&quot; name=&quot;content_message&quot; type=&quot;xs:string&quot;/&gt;
    &lt;/xs:sequence&gt;
  &lt;/xs:complexType&gt;

  &lt;xs:complexType name=&quot;makeReverseTransactionResponse&quot;&gt;
    &lt;xs:sequence&gt;
      &lt;xs:element minOccurs=&quot;0&quot; name=&quot;return&quot; type=&quot;xs:string&quot;/&gt;
    &lt;/xs:sequence&gt;
  &lt;/xs:complexType&gt;

  &lt;xs:complexType name=&quot;getIncomingTransaction&quot;&gt;
    &lt;xs:sequence&gt;
      &lt;xs:element minOccurs=&quot;0&quot; name=&quot;cm_user_name&quot; type=&quot;xs:string&quot;/&gt;
      &lt;xs:element minOccurs=&quot;0&quot; name=&quot;cm_password&quot; type=&quot;xs:string&quot;/&gt;
      &lt;xs:element minOccurs=&quot;0&quot; name=&quot;payee_participant_code&quot; type=&quot;xs:string&quot;/&gt;
    &lt;/xs:sequence&gt;
  &lt;/xs:complexType&gt;

  &lt;xs:complexType name=&quot;getIncomingTransactionResponse&quot;&gt;
    &lt;xs:sequence&gt;
      &lt;xs:element minOccurs=&quot;0&quot; name=&quot;return&quot; type=&quot;xs:string&quot;/&gt;
    &lt;/xs:sequence&gt;
  &lt;/xs:complexType&gt;

  &lt;xs:complexType name=&quot;makeAcknowledgment&quot;&gt;
    &lt;xs:sequence&gt;
      &lt;xs:element minOccurs=&quot;0&quot; name=&quot;cm_user_name&quot; type=&quot;xs:string&quot;/&gt;
      &lt;xs:element minOccurs=&quot;0&quot; name=&quot;cm_password&quot; type=&quot;xs:string&quot;/&gt;
      &lt;xs:element minOccurs=&quot;0&quot; name=&quot;content_message&quot; type=&quot;xs:string&quot;/&gt;
    &lt;/xs:sequence&gt;
  &lt;/xs:complexType&gt;

  &lt;xs:complexType name=&quot;makeAcknowledgmentResponse&quot;&gt;
    &lt;xs:sequence&gt;
      &lt;xs:element minOccurs=&quot;0&quot; name=&quot;return&quot; type=&quot;xs:string&quot;/&gt;
    &lt;/xs:sequence&gt;
  &lt;/xs:complexType&gt;

&lt;/xs:schema&gt;</string> 
        </void> 
       </object> 
      </void> 
     </object> 
    </void> 
    <void property="rootElementName"> 
     <string>Envelope</string> 
    </void> 
    <void property="structure"> 
     <string>&lt;?xml version=&quot;1.0&quot; encoding=&quot;UTF-8&quot;?&gt;
&lt;xsd:schema xmlns:ns1=&quot;http://schemas.xmlsoap.org/soap/http&quot; xmlns:wsdl=&quot;http://schemas.xmlsoap.org/wsdl/&quot; xmlns:tns=&quot;http://fastwebservice.nbc.org.kh/&quot; xmlns:xsd=&quot;http://www.w3.org/2001/XMLSchema&quot; xmlns:soap=&quot;http://schemas.xmlsoap.org/wsdl/soap/&quot; xmlns:ftns=&quot;http://fastwebservice.nbc.org.kh/getOutgoingTransaction/Input&quot; targetNamespace=&quot;http://fastwebservice.nbc.org.kh/getOutgoingTransaction/Input&quot;&gt;
   &lt;xsd:import namespace=&quot;http://fastwebservice.nbc.org.kh/&quot;/&gt;
   &lt;xsd:element name=&quot;Envelope&quot;&gt;
      &lt;xsd:complexType&gt;
         &lt;xsd:sequence&gt;
            &lt;xsd:element ref=&quot;ftns:Header&quot;/&gt;
            &lt;xsd:element ref=&quot;ftns:Body&quot;/&gt;
         &lt;/xsd:sequence&gt;
      &lt;/xsd:complexType&gt;
   &lt;/xsd:element&gt;
   &lt;xsd:element name=&quot;Header&quot;&gt;
      &lt;xsd:complexType&gt;
         &lt;xsd:sequence/&gt;
      &lt;/xsd:complexType&gt;
   &lt;/xsd:element&gt;
   &lt;xsd:element name=&quot;Body&quot;&gt;
      &lt;xsd:complexType&gt;
         &lt;xsd:sequence&gt;
            &lt;xsd:element ref=&quot;tns:getOutgoingTransaction&quot;/&gt;
         &lt;/xsd:sequence&gt;
      &lt;/xsd:complexType&gt;
   &lt;/xsd:element&gt;
&lt;/xsd:schema&gt;</string> 
    </void> 
    <void property="targetNamespace"> 
     <string>http://fastwebservice.nbc.org.kh/getOutgoingTransaction/Input</string> 
    </void> 
   </object> 
  </void> 
 </object> 
</java> 
